hkr/Nawabi.py
hkr/__init__.py
hkr-0.1.dist-info/licenses/LICENSE
hkr-0.1.dist-info/METADATA
hkr-0.1.dist-info/WHEEL
hkr-0.1.dist-info/top_level.txt
hkr-0.1.dist-info/RECORD
