Metadata-Version: 2.4
Name: hkr
Version: 0.1
Summary: Simple
Author: Joker
Author-email: jokerspubg993@gmail.com
Classifier: Programming Language :: Python :: 3
Classifier: License :: OSI Approved :: MIT License
Classifier: Operating System :: OS Independent
License-File: LICENSE
Dynamic: author
Dynamic: author-email
Dynamic: classifier
Dynamic: license-file
Dynamic: summary
